vankrupt_workshop_client/README.md
vankrupt_workshop_client/__init__.py
vankrupt_workshop_client/api/README.md
vankrupt_workshop_client/api/__init__.py
vankrupt_workshop_client/api/api_entities.py
vankrupt_workshop_client/api/consumer.py
vankrupt_workshop_client/api/creator.py
vankrupt_workshop_client/consumer_cli.py
vankrupt_workshop_client/creator_cli.py
vankrupt_workshop_client-0.3.0.dist-info/entry_points.txt
vankrupt_workshop_client-0.3.0.dist-info/WHEEL
vankrupt_workshop_client-0.3.0.dist-info/METADATA
vankrupt_workshop_client-0.3.0.dist-info/RECORD
