Metadata-Version: 2.1
Name: vankrupt-workshop-client
Version: 0.3.0
Summary: Reference clients for vankrupt workshop
Author: MeRuslan
Author-email: clanghopper@gmail.com
Requires-Python: >=3.8,<4.0
Classifier: Programming Language :: Python :: 3
Classifier: Programming Language :: Python :: 3.10
Classifier: Programming Language :: Python :: 3.8
Classifier: Programming Language :: Python :: 3.9
Requires-Dist: appdirs (>=1.4.4,<2.0.0)
Requires-Dist: click (>=8.0.1,<9.0.0)
Requires-Dist: dacite (>=1.6.0,<2.0.0)
Requires-Dist: requests (>=2.26.0,<3.0.0)
